{
	"status": "1",
	"data": {
		"base": {
			"poi_tag": "",
			"code": "430105",
			"importance_vip_flag": 0,
			"city_adcode": "430100",
			"telephone": "0731-88873787",
			"new_type": "110101",
			"new_keytype": "风景名胜;公园广场;公园",
			"checked": "1",
			"title": "风景名胜",
			"cre_flag": 0,
			"std_t_tag_0_v": "公园",
			"navi_geometry": "113.040446,28.236921",
			"classify": "公园广场",
			"business": "hotel",
			"sp_mark": 0,
			"shop_info": {
				"claim": 2
			},
			"poi_tag_has_t_tag": 0,
			"pixelx": "218501262",
			"pixely": "112254202",
			"city_name": "长沙市",
			"poiid": "B02DB05NPU",
			"distance": 0,
			"name": "月湖公园",
			"geodata": {
				"aoi": [{
					"name": "月湖公园",
					"mainpoi": "B02DB05NPU",
					"area": 470110.267457
				}]
			},
			"end_poi_extension": "0",
			"y": "28.237564",
			"x": "113.033027",
			"address": "长沙市开福区万家丽北路与三一大道交汇处西北角",
			"tag": "风景名胜;公园广场;公园",
			"picLen": 5
		},
		"spec": {
			"mining_shape": {
				"aoiid": "G00AOI000001XNIW",
				"center": "113.033027,28.237564",
				"area": "470110.267457",
				"sp_type": "3320",
				"shape": "113.034328,28.238028;113.034794,28.237993;113.035191,28.23811;113.035967,28.238064;113.036184,28.238504;113.036273,28.238697;113.036348,28.238816;113.036958,28.238834;113.037064,28.238762;113.037379,28.238519;113.037657,28.238376;113.038115,28.238189;113.038652,28.23783;113.038933,28.237741;113.039516,28.23775;113.039514,28.23793;113.039888,28.238087;113.040377,28.2381;113.040366,28.237714;113.040354,28.237379;113.040333,28.237313;113.04031,28.236936;113.039991,28.236953;113.039526,28.236956;113.039534,28.236592;113.03951,28.236116;113.039492,28.23595;113.039379,28.235671;113.03929,28.235533;113.039191,28.235432;113.038899,28.235213;113.03873,28.235143;113.038555,28.235064;113.037604,28.234781;113.037237,28.234721;113.036919,28.234702;113.03576,28.234645;113.031703,28.234523;113.028264,28.234416;113.028159,28.234491;113.027975,28.237865;113.027941,28.238599;113.027854,28.2391;113.027586,28.23961;113.027388,28.239898;113.027217,28.240082;113.027235,28.240184;113.027294,28.240295;113.027379,28.240353;113.027947,28.240346;113.02843,28.240377;113.028798,28.240413;113.028838,28.240216;113.028987,28.239944;113.029265,28.240116;113.0294,28.240162;113.029558,28.240186;113.029819,28.240149;113.030084,28.24016;113.03007,28.240289;113.030189,28.24033;113.030167,28.240442;113.030562,28.240561;113.031126,28.240691;113.031441,28.240844;113.03169,28.240957;113.032633,28.241155;113.032694,28.241071;113.032657,28.241;113.032265,28.240896;113.032083,28.240739;113.031988,28.240633;113.031955,28.240519;113.031893,28.240515;113.031895,28.24022;113.031798,28.240212;113.031801,28.23988;113.031811,28.239478;113.031865,28.239326;113.031849,28.239219;113.031801,28.239201;113.031823,28.239131;113.031858,28.239039;113.03202,28.238922;113.032217,28.238722;113.032597,28.238593;113.032744,28.238568;113.033021,28.23853;113.033264,28.238421;113.033881,28.238109;113.034328,28.238028",
				"level": 16,
				"type": "0"
			},
			"sp_pic": []
		},
		"pic_cover": {
			"url": "http://store.is.autonavi.com/showpic/1402aaf22b4c78ce14ae2fbad96c4a1b"
		},
		"pic": [{
			"url": "http://store.is.autonavi.com/showpic/1402aaf22b4c78ce14ae2fbad96c4a1b?type=pic",
			"text_sensibility": "2",
			"weight": 998,
			"title": "月湖公园[湖南长沙]"
		}, {
			"url": "http://store.is.autonavi.com/showpic/8d64c7bfebb2c90dc009968260cd3c0d?type=pic",
			"text_sensibility": "2",
			"weight": 997
		}, {
			"url": "http://store.is.autonavi.com/showpic/c48d82a1054e5b490f90af16c601dc7d?type=pic",
			"text_sensibility": "2",
			"weight": 996,
			"title": "月湖公园[湖南长沙]"
		}, {
			"iscover": "1",
			"srcheight": 440,
			"url": "http://store.is.autonavi.com/showpic/22c8c52445b0dc99861ab2b5976d6186?type=pic",
			"text_sensibility": "2",
			"biz": "scenic",
			"pic_id": "22c8c52445b0dc99861ab2b5976d6186",
			"srcwidth": 665,
			"fetch_type": "1"
		}],
		"deep": {
			"src_type_mix": "hotel_taobaolvxing_api",
			"src_id": "55850068",
			"business": "hotel",
			"info_wapurl": "http://h5.m.taobao.com/trip/hotel/detail/detail.html?curcitycode=430100&ttid=12gao0000003&shid=55850068",
			"info_weburl": "http://kezhan.trip.taobao.com/hotel_detail2.htm?shid=55850068",
			"src_type": "cms_deep_merge"
		},
		"rti": {
			"review_entrance": 1,
			"isHaveHotel": "true",
			"review_count": 185,
			"review_labels": [],
			"review_summary": "",
			"has_discount_flag": 0
		},
		"review": {
			"comment": [{
				"quality_flag": 48,
				"author_profileurl": "http://store.is.autonavi.com/showpic/2d8cfb1efc1618ac7e3866535c0258b5",
				"review_wapurl": "http://m.dianping.com/shop/review/577032647",
				"labels": [],
				"src_name": "大众点评",
				"review_appurl": {
					"ios_appurl": "",
					"android_appurl": ""
				},
				"gold_type": "23",
				"pic_info": [{
					"url": "http://store.is.autonavi.com/showpic/c5b388f50129b72ff5e91a4d4dda9544",
					"source": "图片来源：大众点评"
				}, {
					"url": "http://store.is.autonavi.com/showpic/e59ec18e817a7c3604193eadaa9c73ca",
					"source": "图片来源：大众点评"
				}, {
					"url": "http://store.is.autonavi.com/showpic/e2b245ac2708800a80a57ee4dae79a41",
					"source": "图片来源：大众点评"
				}],
				"author": "鬼灯",
				"review": "环境不错。\n荷花还没全开。\n\n有个5、6岁的小女孩在大大咧咧的在路边大便。她奶奶还是外婆还在旁边吊嗓子，你咋不鼓鼓掌呢？\n她奶奶知道厕所就在十米开外，说小孩忍不住。呵呵。\n真是服了。再忍不住至少去旁边草丛里遮挡遮挡吧。裤子一脱就路边大便是原始社会？小小年龄不教教羞耻心，到时候发生什么无法挽回的事情哭也没用了。\n之前跟团旅行也是，做妈的就在厕所门口让小男孩尿尿……无fxxk说。",
				"score": 4,
				"recommend": "",
				"src_type": "dp_mapi",
				"review_id": "577032647",
				"review_weburl": "",
				"gaode_coin": 20,
				"like_num": "0",
				"aos_tag_score": 24,
				"high_quality": 0,
				"gold_num": 2,
				"time": "2019-07-10",
				"author_id": ""
			}, {
				"quality_flag": 48,
				"author_profileurl": "http://store.is.autonavi.com/showpic/99321529e94b07e4b4035ee46559b65c",
				"review_wapurl": "http://m.dianping.com/shop/review/575154924",
				"labels": [],
				"src_name": "大众点评",
				"review_appurl": {
					"ios_appurl": "",
					"android_appurl": ""
				},
				"gold_type": "23",
				"pic_info": [{
					"url": "http://store.is.autonavi.com/showpic/5e94f1f048b3d45deba24e04f8bd30a0",
					"source": "图片来源：大众点评"
				}, {
					"url": "http://store.is.autonavi.com/showpic/60dbc5eb791b051892df48ada509a0a8",
					"source": "图片来源：大众点评"
				}, {
					"url": "http://store.is.autonavi.com/showpic/c263fea3c031aca1ba2bdfda74919ee5",
					"source": "图片来源：大众点评"
				}],
				"author": "漠上花",
				"review": "环境十分舒适，月湖公园里面有许多的杨梅树，图书室，大大小小的观景亭，餐厅，傍晚在月湖公园里面还有两个大团队的广场舞，青春活力街舞型，形态优雅体操型。有小孩子玩的娱乐场所，也有小孩大人玩的水上活动，像游船，水中茶室等，夏天还可以欣赏到一片荷花池，傍晚绕湖走走，一天的疲惫也会消失不见。大家可以到这边来走走。",
				"score": 5,
				"recommend": "",
				"src_type": "dp_mapi",
				"review_id": "575154924",
				"review_weburl": "",
				"gaode_coin": 20,
				"like_num": "0",
				"aos_tag_score": 24,
				"high_quality": 0,
				"gold_num": 2,
				"time": "2019-07-06",
				"author_id": ""
			}]
		},
		"src_info": [],
		"share_url": "http://wb.amap.com/?p=B02DB05NPU%2C28.237564%2C113.033027%2C%E6%9C%88%E6%B9%96%E5%85%AC%E5%9B%AD%2C%E9%95%BF%E6%B2%99%E5%B8%82%E5%BC%80%E7%A6%8F%E5%8C%BA%E4%B8%87%E5%AE%B6%E4%B8%BD%E5%8C%97%E8%B7%AF%E4%B8%8E%E4%B8%89%E4%B8%80%E5%A4%A7%E9%81%93%E4%BA%A4%E6%B1%87%E5%A4%84%E8%A5%BF%E5%8C%97%E8%A7%92"
	}
}